invenio_oaiserver/__init__.py
invenio_oaiserver/admin.py
invenio_oaiserver/config.py
invenio_oaiserver/errors.py
invenio_oaiserver/ext.py
invenio_oaiserver/fetchers.py
invenio_oaiserver/minters.py
invenio_oaiserver/models.py
invenio_oaiserver/percolator.py
invenio_oaiserver/provider.py
invenio_oaiserver/proxies.py
invenio_oaiserver/query.py
invenio_oaiserver/receivers.py
invenio_oaiserver/response.py
invenio_oaiserver/resumption_token.py
invenio_oaiserver/utils.py
invenio_oaiserver/verbs.py
invenio_oaiserver/alembic/5d25c1981985_add_system_created_field.py
invenio_oaiserver/alembic/759d47cbdba7_create_oaiserver_branch.py
invenio_oaiserver/alembic/e655021de0de_create_oiaserver_tables.py
invenio_oaiserver/schemas/__init__.py
invenio_oaiserver/schemas/oaiserver/internal-v1.0.0.json
invenio_oaiserver/schemas/oaiserver/internal-v1.1.0.json
invenio_oaiserver/search/__init__.py
invenio_oaiserver/search/component_templates/__init__.py
invenio_oaiserver/search/component_templates/os-v2/__init__.py
invenio_oaiserver/search/component_templates/os-v2/oairecord-v1.0.0.json
invenio_oaiserver/search/component_templates/v7/__init__.py
invenio_oaiserver/search/component_templates/v7/oairecord-v1.0.0.json
invenio_oaiserver/static/xsl/MARC21slim2OAIDC.xsl
invenio_oaiserver/static/xsl/MARC21slimUtils.xsl
invenio_oaiserver/translations/messages.pot
invenio_oaiserver/translations/ar/LC_MESSAGES/messages.mo
invenio_oaiserver/translations/ar/LC_MESSAGES/messages.po
invenio_oaiserver/translations/bg/LC_MESSAGES/messages.mo
invenio_oaiserver/translations/bg/LC_MESSAGES/messages.po
invenio_oaiserver/translations/ca/LC_MESSAGES/messages.mo
invenio_oaiserver/translations/ca/LC_MESSAGES/messages.po
invenio_oaiserver/translations/cs/LC_MESSAGES/messages.mo
invenio_oaiserver/translations/cs/LC_MESSAGES/messages.po
invenio_oaiserver/translations/da/LC_MESSAGES/messages.mo
invenio_oaiserver/translations/da/LC_MESSAGES/messages.po
invenio_oaiserver/translations/de/LC_MESSAGES/messages.mo
invenio_oaiserver-3.7.4.dist-info/licenses/AUTHORS.rst
invenio_oaiserver-3.7.4.dist-info/licenses/LICENSE
invenio_oaiserver-3.7.4.dist-info/METADATA
invenio_oaiserver-3.7.4.dist-info/WHEEL
invenio_oaiserver-3.7.4.dist-info/entry_points.txt
invenio_oaiserver-3.7.4.dist-info/top_level.txt
invenio_oaiserver-3.7.4.dist-info/RECORD
