Metadata-Version: 2.4
Name: invenio-oaiserver
Version: 3.7.4
Summary: "Invenio module that implements OAI-PMH server."
Home-page: https://github.com/inveniosoftware/invenio-oaiserver
Author: CERN
Author-email: info@inveniosoftware.org
License: MIT
Keywords: invenio OAI-PMH
Platform: any
Classifier: Development Status :: 5 - Production/Stable
Requires-Python: >=3.7
License-File: LICENSE
License-File: AUTHORS.rst
Requires-Dist: arrow>=0.17.0
Requires-Dist: dojson<2.0.0,>=1.3.0
Requires-Dist: invenio-base<3.0.0,>=2.0.0
Requires-Dist: invenio-i18n<4.0.0,>=3.0.0
Requires-Dist: invenio-pidstore<3.0.0,>=2.0.0
Requires-Dist: invenio-records<4.0.0,>=3.0.0
Requires-Dist: invenio-rest<3.0.0,>=2.0.0
Requires-Dist: lxml>=4.3.0
Provides-Extra: tests
Requires-Dist: pytest-black-ng>=0.4.0; extra == "tests"
Requires-Dist: invenio-indexer<4.0.0,>=3.0.0; extra == "tests"
Requires-Dist: invenio-jsonschemas<3.0.0,>=2.0.0; extra == "tests"
Requires-Dist: mock>=1.3.0; extra == "tests"
Requires-Dist: pytest-invenio<4.0.0,>=3.0.0; extra == "tests"
Requires-Dist: invenio-admin<2.0.0,>=1.3.0; extra == "tests"
Requires-Dist: invenio-celery<3.0.0,>=2.0.0; extra == "tests"
Requires-Dist: Sphinx>=4.5.0; extra == "tests"
Requires-Dist: invenio-db[mysql,postgresql,versioning]<3.0.0,>=2.0.0; extra == "tests"
Provides-Extra: elasticsearch7
Requires-Dist: invenio-search[elasticsearch7]<4.0.0,>=3.0.0; extra == "elasticsearch7"
Provides-Extra: opensearch1
Requires-Dist: invenio-search[opensearch1]<4.0.0,>=3.0.0; extra == "opensearch1"
Provides-Extra: opensearch2
Requires-Dist: invenio-search[opensearch2]<4.0.0,>=3.0.0; extra == "opensearch2"
Dynamic: license-file
